Metadata-Version: 2.1
Name: cacheless-airflow
Version: 1.9.0
Summary: Programmatically author, schedule and monitor data pipelines
Home-page: http://airflow.incubator.apache.org/
Author: BBOXX
Author-email: a.nita@bboxx.co.uk
License: Apache License 2.0
Download-URL: https://dist.apache.org/repos/dist/release/incubator/airflow/1.9.0
Platform: UNKNOWN
Classifier: Development Status :: 5 - Production/Stable
Classifier: Environment :: Console
Classifier: Environment :: Web Environment
Classifier: Intended Audience :: Developers
Classifier: Intended Audience :: System Administrators
Classifier: License :: OSI Approved :: Apache Software License
Classifier: Programming Language :: Python :: 2.7
Classifier: Programming Language :: Python :: 3.4
Classifier: Topic :: System :: Monitoring
Requires-Dist: alembic (<0.9,>=0.8.3)
Requires-Dist: bleach (==2.1.2)
Requires-Dist: configparser (<3.6.0,>=3.5.0)
Requires-Dist: croniter (<0.4,>=0.3.17)
Requires-Dist: dill (<0.3,>=0.2.2)
Requires-Dist: flask (<0.12,>=0.11)
Requires-Dist: flask-admin (==1.4.1)
Requires-Dist: flask-cache (<0.14,>=0.13.1)
Requires-Dist: flask-login (==0.2.11)
Requires-Dist: flask-swagger (==0.2.13)
Requires-Dist: flask-wtf (==0.14)
Requires-Dist: funcsigs (==1.0.0)
Requires-Dist: future (<0.17,>=0.16.0)
Requires-Dist: gitpython (>=2.0.2)
Requires-Dist: gunicorn (<20.0,>=19.4.0)
Requires-Dist: jinja2 (<2.9.0,>=2.7.3)
Requires-Dist: lxml (<4.0,>=3.6.0)
Requires-Dist: markdown (<3.0,>=2.5.2)
Requires-Dist: pandas (<1.0.0,>=0.17.1)
Requires-Dist: psutil (<5.0.0,>=4.2.0)
Requires-Dist: pygments (<3.0,>=2.0.1)
Requires-Dist: python-daemon (<2.2,>=2.1.1)
Requires-Dist: python-dateutil (<3,>=2.3)
Requires-Dist: python-nvd3 (==0.14.2)
Requires-Dist: requests (<3,>=2.5.1)
Requires-Dist: setproctitle (<2,>=1.1.8)
Requires-Dist: sqlalchemy (>=0.9.8)
Requires-Dist: tabulate (<0.8.0,>=0.7.5)
Requires-Dist: thrift (>=0.9.2)
Requires-Dist: zope.deprecation (<5.0,>=4.0)
Provides-Extra: all
Requires-Dist: click; extra == 'all'
Requires-Dist: freezegun; extra == 'all'
Requires-Dist: jira; extra == 'all'
Requires-Dist: lxml (>=3.3.4); extra == 'all'
Requires-Dist: mock; extra == 'all'
Requires-Dist: moto (==1.1.19); extra == 'all'
Requires-Dist: nose; extra == 'all'
Requires-Dist: nose-ignore-docstring (==0.2); extra == 'all'
Requires-Dist: nose-timer; extra == 'all'
Requires-Dist: parameterized; extra == 'all'
Requires-Dist: rednose; extra == 'all'
Requires-Dist: paramiko; extra == 'all'
Requires-Dist: requests-mock; extra == 'all'
Requires-Dist: psycopg2 (>=2.7.1); extra == 'all'
Requires-Dist: mysqlclient (>=1.3.6); extra == 'all'
Requires-Dist: hive-thrift-py (>=0.0.1); extra == 'all'
Requires-Dist: pyhive (>=0.1.3); extra == 'all'
Requires-Dist: impyla (>=0.13.3); extra == 'all'
Requires-Dist: unicodecsv (>=0.14.1); extra == 'all'
Requires-Dist: pymssql (>=2.1.1); extra == 'all'
Requires-Dist: snakebite (>=2.7.8); extra == 'all'
Requires-Dist: vertica-python (>=0.5.1); extra == 'all'
Requires-Dist: cloudant (<2.0,>=0.5.9); extra == 'all'
Requires-Dist: sphinx (>=1.2.3); extra == 'all'
Requires-Dist: sphinx-argparse (>=0.1.13); extra == 'all'
Requires-Dist: sphinx-rtd-theme (>=0.1.6); extra == 'all'
Requires-Dist: Sphinx-PyPI-upload (>=0.2.1); extra == 'all'
Requires-Dist: pysmbclient (>=0.1.3); extra == 'all'
Requires-Dist: boto (>=2.36.0); extra == 'all'
Requires-Dist: filechunkio (>=1.6); extra == 'all'
Requires-Dist: slackclient (>=1.0.0); extra == 'all'
Requires-Dist: cryptography (>=0.9.3); extra == 'all'
Requires-Dist: cx-Oracle (>=5.1.2); extra == 'all'
Requires-Dist: docker-py (>=1.6.0); extra == 'all'
Requires-Dist: paramiko (>=2.1.1); extra == 'all'
Provides-Extra: all_dbs
Requires-Dist: psycopg2 (>=2.7.1); extra == 'all_dbs'
Requires-Dist: mysqlclient (>=1.3.6); extra == 'all_dbs'
Requires-Dist: hive-thrift-py (>=0.0.1); extra == 'all_dbs'
Requires-Dist: pyhive (>=0.1.3); extra == 'all_dbs'
Requires-Dist: impyla (>=0.13.3); extra == 'all_dbs'
Requires-Dist: unicodecsv (>=0.14.1); extra == 'all_dbs'
Requires-Dist: pymssql (>=2.1.1); extra == 'all_dbs'
Requires-Dist: snakebite (>=2.7.8); extra == 'all_dbs'
Requires-Dist: vertica-python (>=0.5.1); extra == 'all_dbs'
Requires-Dist: cloudant (<2.0,>=0.5.9); extra == 'all_dbs'
Provides-Extra: async
Requires-Dist: greenlet (>=0.4.9); extra == 'async'
Requires-Dist: eventlet (>=0.9.7); extra == 'async'
Requires-Dist: gevent (>=0.13); extra == 'async'
Provides-Extra: azure
Requires-Dist: azure-storage (>=0.34.0); extra == 'azure'
Provides-Extra: celery
Requires-Dist: celery (>=4.0.0); extra == 'celery'
Requires-Dist: flower (>=0.7.3); extra == 'celery'
Provides-Extra: cgroups
Requires-Dist: cgroupspy (>=0.1.4); extra == 'cgroups'
Provides-Extra: cloudant
Requires-Dist: cloudant (<2.0,>=0.5.9); extra == 'cloudant'
Provides-Extra: crypto
Requires-Dist: cryptography (>=0.9.3); extra == 'crypto'
Provides-Extra: dask
Requires-Dist: distributed (<2,>=1.15.2); extra == 'dask'
Provides-Extra: databricks
Requires-Dist: requests (<3,>=2.5.1); extra == 'databricks'
Provides-Extra: datadog
Requires-Dist: datadog (>=0.14.0); extra == 'datadog'
Provides-Extra: devel
Requires-Dist: click; extra == 'devel'
Requires-Dist: freezegun; extra == 'devel'
Requires-Dist: jira; extra == 'devel'
Requires-Dist: lxml (>=3.3.4); extra == 'devel'
Requires-Dist: mock; extra == 'devel'
Requires-Dist: moto (==1.1.19); extra == 'devel'
Requires-Dist: nose; extra == 'devel'
Requires-Dist: nose-ignore-docstring (==0.2); extra == 'devel'
Requires-Dist: nose-timer; extra == 'devel'
Requires-Dist: parameterized; extra == 'devel'
Requires-Dist: rednose; extra == 'devel'
Requires-Dist: paramiko; extra == 'devel'
Requires-Dist: requests-mock; extra == 'devel'
Requires-Dist: mysqlclient (>=1.3.6); extra == 'devel'
Requires-Dist: sphinx (>=1.2.3); extra == 'devel'
Requires-Dist: sphinx-argparse (>=0.1.13); extra == 'devel'
Requires-Dist: sphinx-rtd-theme (>=0.1.6); extra == 'devel'
Requires-Dist: Sphinx-PyPI-upload (>=0.2.1); extra == 'devel'
Requires-Dist: bcrypt (>=2.0.0); extra == 'devel'
Requires-Dist: flask-bcrypt (>=0.7.1); extra == 'devel'
Requires-Dist: boto (>=2.36.0); extra == 'devel'
Requires-Dist: filechunkio (>=1.6); extra == 'devel'
Requires-Dist: cgroupspy (>=0.1.4); extra == 'devel'
Provides-Extra: devel_hadoop
Requires-Dist: click; extra == 'devel_hadoop'
Requires-Dist: freezegun; extra == 'devel_hadoop'
Requires-Dist: jira; extra == 'devel_hadoop'
Requires-Dist: lxml (>=3.3.4); extra == 'devel_hadoop'
Requires-Dist: mock; extra == 'devel_hadoop'
Requires-Dist: moto (==1.1.19); extra == 'devel_hadoop'
Requires-Dist: nose; extra == 'devel_hadoop'
Requires-Dist: nose-ignore-docstring (==0.2); extra == 'devel_hadoop'
Requires-Dist: nose-timer; extra == 'devel_hadoop'
Requires-Dist: parameterized; extra == 'devel_hadoop'
Requires-Dist: rednose; extra == 'devel_hadoop'
Requires-Dist: paramiko; extra == 'devel_hadoop'
Requires-Dist: requests-mock; extra == 'devel_hadoop'
Requires-Dist: mysqlclient (>=1.3.6); extra == 'devel_hadoop'
Requires-Dist: sphinx (>=1.2.3); extra == 'devel_hadoop'
Requires-Dist: sphinx-argparse (>=0.1.13); extra == 'devel_hadoop'
Requires-Dist: sphinx-rtd-theme (>=0.1.6); extra == 'devel_hadoop'
Requires-Dist: Sphinx-PyPI-upload (>=0.2.1); extra == 'devel_hadoop'
Requires-Dist: bcrypt (>=2.0.0); extra == 'devel_hadoop'
Requires-Dist: flask-bcrypt (>=0.7.1); extra == 'devel_hadoop'
Requires-Dist: boto (>=2.36.0); extra == 'devel_hadoop'
Requires-Dist: filechunkio (>=1.6); extra == 'devel_hadoop'
Requires-Dist: cgroupspy (>=0.1.4); extra == 'devel_hadoop'
Requires-Dist: hive-thrift-py (>=0.0.1); extra == 'devel_hadoop'
Requires-Dist: pyhive (>=0.1.3); extra == 'devel_hadoop'
Requires-Dist: impyla (>=0.13.3); extra == 'devel_hadoop'
Requires-Dist: unicodecsv (>=0.14.1); extra == 'devel_hadoop'
Requires-Dist: snakebite (>=2.7.8); extra == 'devel_hadoop'
Requires-Dist: hdfs[kerberos,avro,dataframe] (>=2.0.4); extra == 'devel_hadoop'
Requires-Dist: pykerberos (>=1.1.13); extra == 'devel_hadoop'
Requires-Dist: requests-kerberos (>=0.10.0); extra == 'devel_hadoop'
Requires-Dist: thrift-sasl (>=0.2.0); extra == 'devel_hadoop'
Requires-Dist: snakebite[kerberos] (>=2.7.8); extra == 'devel_hadoop'
Requires-Dist: kerberos (>=1.2.5); extra == 'devel_hadoop'
Provides-Extra: doc
Requires-Dist: sphinx (>=1.2.3); extra == 'doc'
Requires-Dist: sphinx-argparse (>=0.1.13); extra == 'doc'
Requires-Dist: sphinx-rtd-theme (>=0.1.6); extra == 'doc'
Requires-Dist: Sphinx-PyPI-upload (>=0.2.1); extra == 'doc'
Provides-Extra: docker
Requires-Dist: docker-py (>=1.6.0); extra == 'docker'
Provides-Extra: emr
Requires-Dist: boto3 (>=1.0.0); extra == 'emr'
Provides-Extra: gcp_api
Requires-Dist: httplib2; extra == 'gcp_api'
Requires-Dist: google-api-python-client (<1.6.0,>=1.5.0); extra == 'gcp_api'
Requires-Dist: oauth2client (<2.1.0,>=2.0.2); extra == 'gcp_api'
Requires-Dist: PyOpenSSL; extra == 'gcp_api'
Requires-Dist: google-cloud-dataflow; extra == 'gcp_api'
Requires-Dist: pandas-gbq; extra == 'gcp_api'
Provides-Extra: github_enterprise
Requires-Dist: Flask-OAuthlib (>=0.9.1); extra == 'github_enterprise'
Provides-Extra: hdfs
Requires-Dist: snakebite (>=2.7.8); extra == 'hdfs'
Provides-Extra: hive
Requires-Dist: hive-thrift-py (>=0.0.1); extra == 'hive'
Requires-Dist: pyhive (>=0.1.3); extra == 'hive'
Requires-Dist: impyla (>=0.13.3); extra == 'hive'
Requires-Dist: unicodecsv (>=0.14.1); extra == 'hive'
Provides-Extra: jdbc
Requires-Dist: jaydebeapi (>=1.1.1); extra == 'jdbc'
Provides-Extra: jira
Requires-Dist: JIRA (>1.0.7); extra == 'jira'
Provides-Extra: kerberos
Requires-Dist: pykerberos (>=1.1.13); extra == 'kerberos'
Requires-Dist: requests-kerberos (>=0.10.0); extra == 'kerberos'
Requires-Dist: thrift-sasl (>=0.2.0); extra == 'kerberos'
Requires-Dist: snakebite[kerberos] (>=2.7.8); extra == 'kerberos'
Requires-Dist: kerberos (>=1.2.5); extra == 'kerberos'
Provides-Extra: ldap
Requires-Dist: ldap3 (>=0.9.9.1); extra == 'ldap'
Provides-Extra: mssql
Requires-Dist: pymssql (>=2.1.1); extra == 'mssql'
Requires-Dist: unicodecsv (>=0.14.1); extra == 'mssql'
Provides-Extra: mysql
Requires-Dist: mysqlclient (>=1.3.6); extra == 'mysql'
Provides-Extra: oracle
Requires-Dist: cx-Oracle (>=5.1.2); extra == 'oracle'
Provides-Extra: password
Requires-Dist: bcrypt (>=2.0.0); extra == 'password'
Requires-Dist: flask-bcrypt (>=0.7.1); extra == 'password'
Provides-Extra: postgres
Requires-Dist: psycopg2 (>=2.7.1); extra == 'postgres'
Provides-Extra: qds
Requires-Dist: qds-sdk (>=1.9.6); extra == 'qds'
Provides-Extra: rabbitmq
Requires-Dist: librabbitmq (>=1.6.1); extra == 'rabbitmq'
Provides-Extra: redis
Requires-Dist: redis (>=2.10.5); extra == 'redis'
Provides-Extra: s3
Requires-Dist: boto (>=2.36.0); extra == 's3'
Requires-Dist: filechunkio (>=1.6); extra == 's3'
Provides-Extra: salesforce
Requires-Dist: simple-salesforce (>=0.72); extra == 'salesforce'
Provides-Extra: samba
Requires-Dist: pysmbclient (>=0.1.3); extra == 'samba'
Provides-Extra: slack
Requires-Dist: slackclient (>=1.0.0); extra == 'slack'
Provides-Extra: ssh
Requires-Dist: paramiko (>=2.1.1); extra == 'ssh'
Provides-Extra: statsd
Requires-Dist: statsd (<4.0,>=3.0.1); extra == 'statsd'
Provides-Extra: vertica
Requires-Dist: vertica-python (>=0.5.1); extra == 'vertica'
Provides-Extra: webhdfs
Requires-Dist: hdfs[kerberos,avro,dataframe] (>=2.0.4); extra == 'webhdfs'
